{
  "dataset": "miniimagenet",
  "seed": 5,
  "train_cfg": "experiments/bmvc_1256_20260508-124032/generated_configs/bimc_dino_fusion.yaml",
  "method": "sessionwise conservative query prototype refinement on bimc_dino_fusion with pseudo-validation alpha selection",
  "runtime_sec": 447.734,
  "alpha_grid": [
    0.5,
    0.75,
    1.0
  ],
  "alpha_selection": "pseudo_validation_no_test_labels",
  "mass_thr": 0.3,
  "min_count": 5,
  "val_fraction": 0.3,
  "base_val_conf_thr": 0.5,
  "base_val_max_per_class": 50,
  "fallback_alpha": 0.75,
  "topk_per_class": null,
  "baseline_acc_list": [
    97.1,
    96.954,
    95.414,
    95.427,
    95.413,
    94.894,
    94.122,
    93.758,
    93.65
  ],
  "final_acc_list": [
    97.1,
    96.969,
    95.514,
    95.533,
    95.563,
    95.176,
    94.4,
    94.116,
    94.03
  ],
  "gain_list": [
    0.0,
    0.015,
    0.1,
    0.107,
    0.15,
    0.282,
    0.278,
    0.358,
    0.38
  ],
  "baseline_avg": 95.192,
  "baseline_pd": 3.45,
  "final_avg": 95.378,
  "final_pd": 3.07,
  "gain_avg": 0.186,
  "session_results": [
    {
      "session": 0,
      "num_seen_classes": 60,
      "baseline_full_acc": 97.1,
      "baseline_base_acc": 97.1,
      "baseline_novel_acc": 0.0,
      "best_alpha": null,
      "final_full_acc": 97.1,
      "final_base_acc": 97.1,
      "final_novel_acc": 0.0,
      "final_gain": 0.0,
      "updated_class_count": 0,
      "gated_query_count": 0,
      "alpha_selection": {
        "mode": "not_applicable_base_session",
        "selected_alpha": null
      }
    },
    {
      "session": 1,
      "num_seen_classes": 65,
      "baseline_full_acc": 96.954,
      "baseline_base_acc": 97.033,
      "baseline_novel_acc": 96.0,
      "selected_alpha": 0.5,
      "final_full_acc": 96.969,
      "final_base_acc": 97.033,
      "final_novel_acc": 96.2,
      "final_gain": 0.015,
      "updated_class_count": 5,
      "gated_query_count": 489,
      "gated_base_count": 4,
      "gated_novel_count": 485,
      "alpha_selection": {
        "mode": "pseudo_validation",
        "fallback_used": false,
        "selected_alpha": 0.5,
        "candidates": [
          {
            "alpha": 0.5,
            "pseudo_val_score": -0.024533,
            "pseudo_val_nll": 0.024533,
            "pseudo_val_agreement": 99.936
          },
          {
            "alpha": 0.75,
            "pseudo_val_score": -0.02476,
            "pseudo_val_nll": 0.02476,
            "pseudo_val_agreement": 99.873
          },
          {
            "alpha": 1.0,
            "pseudo_val_score": -0.025016,
            "pseudo_val_nll": 0.025016,
            "pseudo_val_agreement": 99.873
          }
        ],
        "split": {
          "novel_gated_query_count": 489,
          "validation_count": 3147,
          "novel_validation_count": 147,
          "base_validation_count": 3000,
          "updated_class_count": 5,
          "per_class_counts": {
            "60": 98,
            "61": 99,
            "62": 93,
            "63": 102,
            "64": 97
          },
          "per_class_update_counts": {
            "60": 69,
            "61": 69,
            "62": 65,
            "63": 71,
            "64": 68
          },
          "per_class_validation_counts": {
            "60": 29,
            "61": 30,
            "62": 28,
            "63": 31,
            "64": 29
          }
        }
      }
    },
    {
      "session": 2,
      "num_seen_classes": 70,
      "baseline_full_acc": 95.414,
      "baseline_base_acc": 96.9,
      "baseline_novel_acc": 86.5,
      "selected_alpha": 0.5,
      "final_full_acc": 95.514,
      "final_base_acc": 96.733,
      "final_novel_acc": 88.2,
      "final_gain": 0.1,
      "updated_class_count": 10,
      "gated_query_count": 881,
      "gated_base_count": 10,
      "gated_novel_count": 871,
      "alpha_selection": {
        "mode": "pseudo_validation",
        "fallback_used": false,
        "selected_alpha": 0.5,
        "candidates": [
          {
            "alpha": 0.5,
            "pseudo_val_score": -0.046616,
            "pseudo_val_nll": 0.046616,
            "pseudo_val_agreement": 99.816
          },
          {
            "alpha": 0.75,
            "pseudo_val_score": -0.048229,
            "pseudo_val_nll": 0.048229,
            "pseudo_val_agreement": 99.724
          },
          {
            "alpha": 1.0,
            "pseudo_val_score": -0.049013,
            "pseudo_val_nll": 0.049013,
            "pseudo_val_agreement": 99.724
          }
        ],
        "split": {
          "novel_gated_query_count": 881,
          "validation_count": 3264,
          "novel_validation_count": 264,
          "base_validation_count": 3000,
          "updated_class_count": 10,
          "per_class_counts": {
            "60": 98,
            "61": 99,
            "62": 93,
            "63": 101,
            "64": 97,
            "65": 76,
            "66": 98,
            "67": 101,
            "68": 26,
            "69": 92
          },
          "per_class_update_counts": {
            "60": 69,
            "61": 69,
            "62": 65,
            "63": 71,
            "64": 68,
            "65": 53,
            "66": 69,
            "67": 71,
            "68": 18,
            "69": 64
          },
          "per_class_validation_counts": {
            "60": 29,
            "61": 30,
            "62": 28,
            "63": 30,
            "64": 29,
            "65": 23,
            "66": 29,
            "67": 30,
            "68": 8,
            "69": 28
          }
        }
      }
    },
    {
      "session": 3,
      "num_seen_classes": 75,
      "baseline_full_acc": 95.427,
      "baseline_base_acc": 96.883,
      "baseline_novel_acc": 89.6,
      "selected_alpha": 0.5,
      "final_full_acc": 95.533,
      "final_base_acc": 96.7,
      "final_novel_acc": 90.867,
      "final_gain": 0.107,
      "updated_class_count": 15,
      "gated_query_count": 1364,
      "gated_base_count": 12,
      "gated_novel_count": 1352,
      "alpha_selection": {
        "mode": "pseudo_validation",
        "fallback_used": false,
        "selected_alpha": 0.5,
        "candidates": [
          {
            "alpha": 0.5,
            "pseudo_val_score": -0.067313,
            "pseudo_val_nll": 0.067313,
            "pseudo_val_agreement": 99.795
          },
          {
            "alpha": 0.75,
            "pseudo_val_score": -0.069164,
            "pseudo_val_nll": 0.069164,
            "pseudo_val_agreement": 99.648
          },
          {
            "alpha": 1.0,
            "pseudo_val_score": -0.070211,
            "pseudo_val_nll": 0.070211,
            "pseudo_val_agreement": 99.589
          }
        ],
        "split": {
          "novel_gated_query_count": 1364,
          "validation_count": 3408,
          "novel_validation_count": 408,
          "base_validation_count": 3000,
          "updated_class_count": 15,
          "per_class_counts": {
            "60": 98,
            "61": 99,
            "62": 93,
            "63": 100,
            "64": 97,
            "65": 76,
            "66": 98,
            "67": 101,
            "68": 26,
            "69": 91,
            "70": 98,
            "71": 93,
            "72": 97,
            "73": 97,
            "74": 100
          },
          "per_class_update_counts": {
            "60": 69,
            "61": 69,
            "62": 65,
            "63": 70,
            "64": 68,
            "65": 53,
            "66": 69,
            "67": 71,
            "68": 18,
            "69": 64,
            "70": 69,
            "71": 65,
            "72": 68,
            "73": 68,
            "74": 70
          },
          "per_class_validation_counts": {
            "60": 29,
            "61": 30,
            "62": 28,
            "63": 30,
            "64": 29,
            "65": 23,
            "66": 29,
            "67": 30,
            "68": 8,
            "69": 27,
            "70": 29,
            "71": 28,
            "72": 29,
            "73": 29,
            "74": 30
          }
        }
      }
    },
    {
      "session": 4,
      "num_seen_classes": 80,
      "baseline_full_acc": 95.413,
      "baseline_base_acc": 96.717,
      "baseline_novel_acc": 91.5,
      "selected_alpha": 0.5,
      "final_full_acc": 95.563,
      "final_base_acc": 96.55,
      "final_novel_acc": 92.6,
      "final_gain": 0.15,
      "updated_class_count": 20,
      "gated_query_count": 1863,
      "gated_base_count": 20,
      "gated_novel_count": 1843,
      "alpha_selection": {
        "mode": "pseudo_validation",
        "fallback_used": false,
        "selected_alpha": 0.5,
        "candidates": [
          {
            "alpha": 0.5,
            "pseudo_val_score": -0.086889,
            "pseudo_val_nll": 0.086889,
            "pseudo_val_agreement": 99.719
          },
          {
            "alpha": 0.75,
            "pseudo_val_score": -0.088824,
            "pseudo_val_nll": 0.088824,
            "pseudo_val_agreement": 99.55
          },
          {
            "alpha": 1.0,
            "pseudo_val_score": -0.090102,
            "pseudo_val_nll": 0.090102,
            "pseudo_val_agreement": 99.494
          }
        ],
        "split": {
          "novel_gated_query_count": 1863,
          "validation_count": 3558,
          "novel_validation_count": 558,
          "base_validation_count": 3000,
          "updated_class_count": 20,
          "per_class_counts": {
            "60": 98,
            "61": 99,
            "62": 93,
            "63": 100,
            "64": 97,
            "65": 79,
            "66": 97,
            "67": 101,
            "68": 27,
            "69": 91,
            "70": 98,
            "71": 92,
            "72": 97,
            "73": 99,
            "74": 100,
            "75": 100,
            "76": 99,
            "77": 100,
            "78": 95,
            "79": 101
          },
          "per_class_update_counts": {
            "60": 69,
            "61": 69,
            "62": 65,
            "63": 70,
            "64": 68,
            "65": 55,
            "66": 68,
            "67": 71,
            "68": 19,
            "69": 64,
            "70": 69,
            "71": 64,
            "72": 68,
            "73": 69,
            "74": 70,
            "75": 70,
            "76": 69,
            "77": 70,
            "78": 67,
            "79": 71
          },
          "per_class_validation_counts": {
            "60": 29,
            "61": 30,
            "62": 28,
            "63": 30,
            "64": 29,
            "65": 24,
            "66": 29,
            "67": 30,
            "68": 8,
            "69": 27,
            "70": 29,
            "71": 28,
            "72": 29,
            "73": 30,
            "74": 30,
            "75": 30,
            "76": 30,
            "77": 30,
            "78": 28,
            "79": 30
          }
        }
      }
    },
    {
      "session": 5,
      "num_seen_classes": 85,
      "baseline_full_acc": 94.894,
      "baseline_base_acc": 96.567,
      "baseline_novel_acc": 90.88,
      "selected_alpha": 0.5,
      "final_full_acc": 95.176,
      "final_base_acc": 96.333,
      "final_novel_acc": 92.4,
      "final_gain": 0.282,
      "updated_class_count": 25,
      "gated_query_count": 2336,
      "gated_base_count": 26,
      "gated_novel_count": 2310,
      "alpha_selection": {
        "mode": "pseudo_validation",
        "fallback_used": false,
        "selected_alpha": 0.5,
        "candidates": [
          {
            "alpha": 0.5,
            "pseudo_val_score": -0.105175,
            "pseudo_val_nll": 0.105175,
            "pseudo_val_agreement": 99.676
          },
          {
            "alpha": 0.75,
            "pseudo_val_score": -0.107292,
            "pseudo_val_nll": 0.107292,
            "pseudo_val_agreement": 99.54
          },
          {
            "alpha": 1.0,
            "pseudo_val_score": -0.108898,
            "pseudo_val_nll": 0.108898,
            "pseudo_val_agreement": 99.513
          }
        ],
        "split": {
          "novel_gated_query_count": 2336,
          "validation_count": 3699,
          "novel_validation_count": 699,
          "base_validation_count": 3000,
          "updated_class_count": 25,
          "per_class_counts": {
            "60": 98,
            "61": 98,
            "62": 93,
            "63": 100,
            "64": 96,
            "65": 79,
            "66": 99,
            "67": 101,
            "68": 27,
            "69": 90,
            "70": 98,
            "71": 91,
            "72": 97,
            "73": 98,
            "74": 100,
            "75": 100,
            "76": 99,
            "77": 100,
            "78": 91,
            "79": 101,
            "80": 96,
            "81": 103,
            "82": 94,
            "83": 99,
            "84": 88
          },
          "per_class_update_counts": {
            "60": 69,
            "61": 69,
            "62": 65,
            "63": 70,
            "64": 67,
            "65": 55,
            "66": 69,
            "67": 71,
            "68": 19,
            "69": 63,
            "70": 69,
            "71": 64,
            "72": 68,
            "73": 69,
            "74": 70,
            "75": 70,
            "76": 69,
            "77": 70,
            "78": 64,
            "79": 71,
            "80": 67,
            "81": 72,
            "82": 66,
            "83": 69,
            "84": 62
          },
          "per_class_validation_counts": {
            "60": 29,
            "61": 29,
            "62": 28,
            "63": 30,
            "64": 29,
            "65": 24,
            "66": 30,
            "67": 30,
            "68": 8,
            "69": 27,
            "70": 29,
            "71": 27,
            "72": 29,
            "73": 29,
            "74": 30,
            "75": 30,
            "76": 30,
            "77": 30,
            "78": 27,
            "79": 30,
            "80": 29,
            "81": 31,
            "82": 28,
            "83": 30,
            "84": 26
          }
        }
      }
    },
    {
      "session": 6,
      "num_seen_classes": 90,
      "baseline_full_acc": 94.122,
      "baseline_base_acc": 96.35,
      "baseline_novel_acc": 89.667,
      "selected_alpha": 0.5,
      "final_full_acc": 94.4,
      "final_base_acc": 96.1,
      "final_novel_acc": 91.0,
      "final_gain": 0.278,
      "updated_class_count": 30,
      "gated_query_count": 2793,
      "gated_base_count": 39,
      "gated_novel_count": 2754,
      "alpha_selection": {
        "mode": "pseudo_validation",
        "fallback_used": false,
        "selected_alpha": 0.5,
        "candidates": [
          {
            "alpha": 0.5,
            "pseudo_val_score": -0.124745,
            "pseudo_val_nll": 0.124745,
            "pseudo_val_agreement": 99.374
          },
          {
            "alpha": 0.75,
            "pseudo_val_score": -0.128523,
            "pseudo_val_nll": 0.128523,
            "pseudo_val_agreement": 99.061
          },
          {
            "alpha": 1.0,
            "pseudo_val_score": -0.132466,
            "pseudo_val_nll": 0.132466,
            "pseudo_val_agreement": 98.853
          }
        ],
        "split": {
          "novel_gated_query_count": 2793,
          "validation_count": 3835,
          "novel_validation_count": 835,
          "base_validation_count": 3000,
          "updated_class_count": 30,
          "per_class_counts": {
            "60": 98,
            "61": 98,
            "62": 93,
            "63": 100,
            "64": 96,
            "65": 77,
            "66": 99,
            "67": 88,
            "68": 27,
            "69": 91,
            "70": 98,
            "71": 91,
            "72": 97,
            "73": 99,
            "74": 100,
            "75": 100,
            "76": 99,
            "77": 100,
            "78": 90,
            "79": 101,
            "80": 98,
            "81": 103,
            "82": 94,
            "83": 99,
            "84": 88,
            "85": 95,
            "86": 110,
            "87": 98,
            "88": 67,
            "89": 99
          },
          "per_class_update_counts": {
            "60": 69,
            "61": 69,
            "62": 65,
            "63": 70,
            "64": 67,
            "65": 54,
            "66": 69,
            "67": 62,
            "68": 19,
            "69": 64,
            "70": 69,
            "71": 64,
            "72": 68,
            "73": 69,
            "74": 70,
            "75": 70,
            "76": 69,
            "77": 70,
            "78": 63,
            "79": 71,
            "80": 69,
            "81": 72,
            "82": 66,
            "83": 69,
            "84": 62,
            "85": 67,
            "86": 77,
            "87": 69,
            "88": 47,
            "89": 69
          },
          "per_class_validation_counts": {
            "60": 29,
            "61": 29,
            "62": 28,
            "63": 30,
            "64": 29,
            "65": 23,
            "66": 30,
            "67": 26,
            "68": 8,
            "69": 27,
            "70": 29,
            "71": 27,
            "72": 29,
            "73": 30,
            "74": 30,
            "75": 30,
            "76": 30,
            "77": 30,
            "78": 27,
            "79": 30,
            "80": 29,
            "81": 31,
            "82": 28,
            "83": 30,
            "84": 26,
            "85": 28,
            "86": 33,
            "87": 29,
            "88": 20,
            "89": 30
          }
        }
      }
    },
    {
      "session": 7,
      "num_seen_classes": 95,
      "baseline_full_acc": 93.758,
      "baseline_base_acc": 96.2,
      "baseline_novel_acc": 89.571,
      "selected_alpha": 0.5,
      "final_full_acc": 94.116,
      "final_base_acc": 95.917,
      "final_novel_acc": 91.029,
      "final_gain": 0.358,
      "updated_class_count": 35,
      "gated_query_count": 3254,
      "gated_base_count": 43,
      "gated_novel_count": 3211,
      "alpha_selection": {
        "mode": "pseudo_validation",
        "fallback_used": false,
        "selected_alpha": 0.5,
        "candidates": [
          {
            "alpha": 0.5,
            "pseudo_val_score": -0.139563,
            "pseudo_val_nll": 0.139563,
            "pseudo_val_agreement": 99.32
          },
          {
            "alpha": 0.75,
            "pseudo_val_score": -0.143701,
            "pseudo_val_nll": 0.143701,
            "pseudo_val_agreement": 98.943
          },
          {
            "alpha": 1.0,
            "pseudo_val_score": -0.148397,
            "pseudo_val_nll": 0.148397,
            "pseudo_val_agreement": 98.616
          }
        ],
        "split": {
          "novel_gated_query_count": 3254,
          "validation_count": 3973,
          "novel_validation_count": 973,
          "base_validation_count": 3000,
          "updated_class_count": 35,
          "per_class_counts": {
            "60": 98,
            "61": 98,
            "62": 93,
            "63": 100,
            "64": 96,
            "65": 75,
            "66": 99,
            "67": 88,
            "68": 27,
            "69": 88,
            "70": 98,
            "71": 91,
            "72": 97,
            "73": 98,
            "74": 100,
            "75": 99,
            "76": 99,
            "77": 99,
            "78": 90,
            "79": 101,
            "80": 98,
            "81": 103,
            "82": 95,
            "83": 99,
            "84": 90,
            "85": 95,
            "86": 110,
            "87": 97,
            "88": 69,
            "89": 100,
            "90": 62,
            "91": 99,
            "92": 95,
            "93": 107,
            "94": 101
          },
          "per_class_update_counts": {
            "60": 69,
            "61": 69,
            "62": 65,
            "63": 70,
            "64": 67,
            "65": 53,
            "66": 69,
            "67": 62,
            "68": 19,
            "69": 62,
            "70": 69,
            "71": 64,
            "72": 68,
            "73": 69,
            "74": 70,
            "75": 69,
            "76": 69,
            "77": 69,
            "78": 63,
            "79": 71,
            "80": 69,
            "81": 72,
            "82": 67,
            "83": 69,
            "84": 63,
            "85": 67,
            "86": 77,
            "87": 68,
            "88": 48,
            "89": 70,
            "90": 43,
            "91": 69,
            "92": 67,
            "93": 75,
            "94": 71
          },
          "per_class_validation_counts": {
            "60": 29,
            "61": 29,
            "62": 28,
            "63": 30,
            "64": 29,
            "65": 22,
            "66": 30,
            "67": 26,
            "68": 8,
            "69": 26,
            "70": 29,
            "71": 27,
            "72": 29,
            "73": 29,
            "74": 30,
            "75": 30,
            "76": 30,
            "77": 30,
            "78": 27,
            "79": 30,
            "80": 29,
            "81": 31,
            "82": 28,
            "83": 30,
            "84": 27,
            "85": 28,
            "86": 33,
            "87": 29,
            "88": 21,
            "89": 30,
            "90": 19,
            "91": 30,
            "92": 28,
            "93": 32,
            "94": 30
          }
        }
      }
    },
    {
      "session": 8,
      "num_seen_classes": 100,
      "baseline_full_acc": 93.65,
      "baseline_base_acc": 96.117,
      "baseline_novel_acc": 89.95,
      "selected_alpha": 0.5,
      "final_full_acc": 94.03,
      "final_base_acc": 95.833,
      "final_novel_acc": 91.325,
      "final_gain": 0.38,
      "updated_class_count": 40,
      "gated_query_count": 3736,
      "gated_base_count": 53,
      "gated_novel_count": 3683,
      "alpha_selection": {
        "mode": "pseudo_validation",
        "fallback_used": false,
        "selected_alpha": 0.5,
        "candidates": [
          {
            "alpha": 0.5,
            "pseudo_val_score": -0.154568,
            "pseudo_val_nll": 0.154568,
            "pseudo_val_agreement": 99.223
          },
          {
            "alpha": 0.75,
            "pseudo_val_score": -0.159104,
            "pseudo_val_nll": 0.159104,
            "pseudo_val_agreement": 98.907
          },
          {
            "alpha": 1.0,
            "pseudo_val_score": -0.164243,
            "pseudo_val_nll": 0.164243,
            "pseudo_val_agreement": 98.543
          }
        ],
        "split": {
          "novel_gated_query_count": 3736,
          "validation_count": 4118,
          "novel_validation_count": 1118,
          "base_validation_count": 3000,
          "updated_class_count": 40,
          "per_class_counts": {
            "60": 98,
            "61": 98,
            "62": 93,
            "63": 99,
            "64": 96,
            "65": 74,
            "66": 99,
            "67": 88,
            "68": 27,
            "69": 90,
            "70": 98,
            "71": 91,
            "72": 97,
            "73": 98,
            "74": 100,
            "75": 99,
            "76": 99,
            "77": 100,
            "78": 90,
            "79": 101,
            "80": 98,
            "81": 103,
            "82": 95,
            "83": 99,
            "84": 90,
            "85": 95,
            "86": 110,
            "87": 97,
            "88": 68,
            "89": 99,
            "90": 62,
            "91": 98,
            "92": 95,
            "93": 108,
            "94": 102,
            "95": 97,
            "96": 96,
            "97": 89,
            "98": 100,
            "99": 100
          },
          "per_class_update_counts": {
            "60": 69,
            "61": 69,
            "62": 65,
            "63": 69,
            "64": 67,
            "65": 52,
            "66": 69,
            "67": 62,
            "68": 19,
            "69": 63,
            "70": 69,
            "71": 64,
            "72": 68,
            "73": 69,
            "74": 70,
            "75": 69,
            "76": 69,
            "77": 70,
            "78": 63,
            "79": 71,
            "80": 69,
            "81": 72,
            "82": 67,
            "83": 69,
            "84": 63,
            "85": 67,
            "86": 77,
            "87": 68,
            "88": 48,
            "89": 69,
            "90": 43,
            "91": 69,
            "92": 67,
            "93": 76,
            "94": 71,
            "95": 68,
            "96": 67,
            "97": 62,
            "98": 70,
            "99": 70
          },
          "per_class_validation_counts": {
            "60": 29,
            "61": 29,
            "62": 28,
            "63": 30,
            "64": 29,
            "65": 22,
            "66": 30,
            "67": 26,
            "68": 8,
            "69": 27,
            "70": 29,
            "71": 27,
            "72": 29,
            "73": 29,
            "74": 30,
            "75": 30,
            "76": 30,
            "77": 30,
            "78": 27,
            "79": 30,
            "80": 29,
            "81": 31,
            "82": 28,
            "83": 30,
            "84": 27,
            "85": 28,
            "86": 33,
            "87": 29,
            "88": 20,
            "89": 30,
            "90": 19,
            "91": 29,
            "92": 28,
            "93": 32,
            "94": 31,
            "95": 29,
            "96": 29,
            "97": 27,
            "98": 30,
            "99": 30
          }
        }
      }
    }
  ]
}